bandori_play/__init__.py
bandori_play/bin/ffplay.exe
bandori_play-0.0.4.dist-info/METADATA
bandori_play-0.0.4.dist-info/WHEEL
bandori_play-0.0.4.dist-info/entry_points.txt
bandori_play-0.0.4.dist-info/top_level.txt
bandori_play-0.0.4.dist-info/RECORD
