Metadata-Version: 2.1
Name: bandori-play
Version: 0.0.4
Summary: Play and download bandori's music.
Home-page: UNKNOWN
Author: kazukazuprogram
Author-email: dbycvil8yiyf7xnlxvh7@yahoo.co.jp
Maintainer: kazukazuprogram
Maintainer-email: dbycvil8yiyf7xnlxvh7@yahoo.co.jp
License: MIT
Platform: UNKNOWN
Requires-Dist: requests
Requires-Dist: bs4
Requires-Dist: lxml
